tensorflow_lattice/BUILD
tensorflow_lattice/__init__.py
tensorflow_lattice/layers/__init__.py
tensorflow_lattice/python/BUILD
tensorflow_lattice/python/__init__.py
tensorflow_lattice/python/aggregation_layer.py
tensorflow_lattice/python/aggregation_test.py
tensorflow_lattice/python/categorical_calibration_layer.py
tensorflow_lattice/python/categorical_calibration_lib.py
tensorflow_lattice/python/categorical_calibration_test.py
tensorflow_lattice/python/cdf_layer.py
tensorflow_lattice/python/cdf_test.py
tensorflow_lattice/python/conditional_cdf.py
tensorflow_lattice/python/conditional_cdf_test.py
tensorflow_lattice/python/conditional_pwl_calibration.py
tensorflow_lattice/python/conditional_pwl_calibration_test.py
tensorflow_lattice/python/configs.py
tensorflow_lattice/python/configs_test.py
tensorflow_lattice/python/internal_utils.py
tensorflow_lattice/python/internal_utils_test.py
tensorflow_lattice/python/kronecker_factored_lattice_layer.py
tensorflow_lattice/python/kronecker_factored_lattice_lib.py
tensorflow_lattice/python/kronecker_factored_lattice_test.py
tensorflow_lattice/python/lattice_layer.py
tensorflow_lattice/python/lattice_lib.py
tensorflow_lattice/python/lattice_test.py
tensorflow_lattice/python/linear_layer.py
tensorflow_lattice/python/linear_lib.py
tensorflow_lattice/python/linear_test.py
tensorflow_lattice/python/model_info.py
tensorflow_lattice/python/parallel_combination_layer.py
tensorflow_lattice/python/parallel_combination_test.py
tensorflow_lattice/python/premade.py
tensorflow_lattice/python/premade_lib.py
tensorflow_lattice/python/premade_test.py
tensorflow_lattice/python/pwl_calibration_layer.py
tensorflow_lattice/python/pwl_calibration_lib.py
tensorflow_lattice/python/pwl_calibration_test.py
tensorflow_lattice/python/rtl_layer.py
tensorflow_lattice/python/rtl_lib.py
tensorflow_lattice/python/rtl_test.py
tensorflow_lattice/python/test_utils.py
tensorflow_lattice/python/utils.py
tensorflow_lattice/python/utils_test.py
tensorflow_lattice-2.1.1.dist-info/AUTHORS
tensorflow_lattice-2.1.1.dist-info/LICENSE
tensorflow_lattice-2.1.1.dist-info/METADATA
tensorflow_lattice-2.1.1.dist-info/WHEEL
tensorflow_lattice-2.1.1.dist-info/top_level.txt
tensorflow_lattice-2.1.1.dist-info/RECORD
